Workbook
Name _AA100000: #REF!
Name _Fill: #REF!
Name _LOC10: #REF!
Name _LOC11: #REF!
Name _LOC12: #REF!
Name _LOC13: #REF!
Name _LOC14: #REF!
Name _LOC15: #REF!
Name _LOC16: #REF!
Name _LOC17: #REF!
Name _LOC18: #REF!
Name _LOC19: #REF!
Name _LOC2: #REF!
Name _LOC20: #REF!
Name _LOC21: #REF!
Name _LOC22: #REF!
Name _LOC23: #REF!
Name _LOC24: #REF!
Name _LOC25: #REF!
Name _LOC26: #REF!
Name _LOC27: #REF!
Name _LOC28: #REF!
Name _LOC29: #REF!
Name _LOC3: #REF!
Name _LOC30: #REF!
Name _LOC31: #REF!
Name _LOC32: #REF!
Name _LOC33: #REF!
Name _LOC34: #REF!
Name _LOC35: #REF!
Name _LOC36: #REF!
Name _LOC37: #REF!
Name _LOC38: #REF!
Name _LOC39: #REF!
Name _LOC4: #REF!
Name _LOC40: #REF!
Name _LOC41: #REF!
Name _LOC42: #REF!
Name _LOC5: #REF!
Name _LOC6: #REF!
Name _LOC7: #REF!
Name _LOC8: #REF!
Name _LOC9: #REF!
Name _R: #REF!
Name AAA: #REF!
Name AC: #REF!
Name AL: #REF!
Name Área_impressão_IM: #REF!
Name B.01.05.10.10: #REF!
Name CD: #REF!
Name CP: #REF!
Name CS: #REF!
Name CT: #REF!
Name EV: #REF!
Name IC: #REF!
Name IMPR: #REF!
Name IMPR1: #REF!
Name IS: #REF!
Name LB: #REF!
Name MACROS: #REF!

Sheet DADOS GERAIS
B2: DADOS GERAIS
B8: Secretaria de Atenção Especializada à Saúde
B9: =C15 -> Policlínica - Área Construída: 3.213,00 m²
B11: Bancos:
B12: SINAPI (11/2023) - CPOS/CDHU (11/2023) - SBC (11/2023) - ORSE (11/2023) - SEINFRA (028) - IOPES (11/2023) - CAERN (11/2023) - EMOP (11/2023)
B15: Obra: | C15: Policlínica - Área Construída: 3.213,00 m²
B16: Local: | C16: Ministério da Saúde - Departamento de Atenção Hospitalar Domiciliar e de Urgência
B17: Região: | C17: SP
B18: Data Base: | C18: 45231
B19: BDI Geral (%): | C19: ='BDI DESONERADO'!E36 -> 0.24875249
B20: BDI Equipamentos (%): | C20: ='BDI DESONERADO'!F36 -> 0.16857591
B21: Área construída (m²): | C21: 3213
B22: Data: | C22: 09/05/2024
B23: Revisão: | C23: 03
B24: Responsável Técnico pelo Orçamento: | C24: Thaís Ferreira Pellaquim
B25: Cargo Responsável Técnico: | C25: Engenheira Civil - CREA MG 247749/D
B31: ________________________________________________________________________________
B32: =C24 -> Thaís Ferreira Pellaquim
B33: =C25 -> Engenheira Civil - CREA MG 247749/D

Sheet RESUMO
B2: PLANILHA RESUMO
B8: ='DADOS GERAIS'!B8 -> Secretaria de Atenção Especializada à Saúde | D8: BDI Geral: | E8: Encargo Social Mensalista: | F8: ='DADOS GERAIS'!$B$22 -> Data:
B9: ='DADOS GERAIS'!B9 -> Policlínica - Área Construída: 3.213,00 m² | D9: ='DADOS GERAIS'!C19 -> 0.24875249 | E9: ='ENCARGOS SOCIAIS'!F56 -> 0.4757 | F9: ='DADOS GERAIS'!$C$22 -> 09/05/2024
B11: ='DADOS GERAIS'!B11 -> Bancos: | D11: BDI Equipamentos: | E11: Encargo Social Horista: | F11: ='DADOS GERAIS'!$B$23 -> Revisão:
B12: ='DADOS GERAIS'!B12 -> SINAPI (11/2023) - CPOS/CDHU (11/2023) - SBC (11/2023) - ORSE (11/2023) - SEINFRA (028) - IOPES (11/2023) - CAERN (11/2023) - EMOP (11/2023) | D12: ='DADOS GERAIS'!C20 -> 0.16857591 | E12: ='ENCARGOS SOCIAIS'!E56 -> 0.8555518 | F12: ='DADOS GERAIS'!$C$23 -> 03
B15: ITEM | C15: DESCRIÇÃO | E15: PREÇO | F15: %
B17: 1 | C17: {=INDEX('ORC. SINTÉTICO'!$E:$E,MATCH($B17,'ORC. SINTÉTICO'!$B:$B,0))} -> SERVIÇOS PRELIMINARES E INDIRETOS | E17: {=INDEX('ORC. SINTÉTICO'!$N:$N,MATCH($B17,'ORC. SINTÉTICO'!$B:$B,0))} -> 0 | F17: =IFERROR(E17/$E$41,"-") -> -
B18: 2 | C18: {=INDEX('ORC. SINTÉTICO'!$E:$E,MATCH($B18,'ORC. SINTÉTICO'!$B:$B,0))} -> FUNDAÇÃO | E18: {=INDEX('ORC. SINTÉTICO'!$N:$N,MATCH($B18,'ORC. SINTÉTICO'!$B:$B,0))} -> 0 | F18: =IFERROR(E18/$E$41,"-") -> -
B19: 3 | C19: {=INDEX('ORC. SINTÉTICO'!$E:$E,MATCH($B19,'ORC. SINTÉTICO'!$B:$B,0))} -> ESTRUTURA | E19: {=INDEX('ORC. SINTÉTICO'!$N:$N,MATCH($B19,'ORC. SINTÉTICO'!$B:$B,0))} -> 0 | F19: =IFERROR(E19/$E$41,"-") -> -
B20: 4 | C20: {=INDEX('ORC. SINTÉTICO'!$E:$E,MATCH($B20,'ORC. SINTÉTICO'!$B:$B,0))} -> ALVENARIA, VEDAÇÕES E DIVISÓRIAS | E20: {=INDEX('ORC. SINTÉTICO'!$N:$N,MATCH($B20,'ORC. SINTÉTICO'!$B:$B,0))} -> 0 | F20: =IFERROR(E20/$E$41,"-") -> -
B21: 5 | C21: {=INDEX('ORC. SINTÉTICO'!$E:$E,MATCH($B21,'ORC. SINTÉTICO'!$B:$B,0))} -> ESQUADRIAS | E21: {=INDEX('ORC. SINTÉTICO'!$N:$N,MATCH($B21,'ORC. SINTÉTICO'!$B:$B,0))} -> 0 | F21: =IFERROR(E21/$E$41,"-") -> -
B22: 6 | C22: {=INDEX('ORC. SINTÉTICO'!$E:$E,MATCH($B22,'ORC. SINTÉTICO'!$B:$B,0))} -> COBERTURA | E22: {=INDEX('ORC. SINTÉTICO'!$N:$N,MATCH($B22,'ORC. SINTÉTICO'!$B:$B,0))} -> 0 | F22: =IFERROR(E22/$E$41,"-") -> -
B23: 7 | C23: {=INDEX('ORC. SINTÉTICO'!$E:$E,MATCH($B23,'ORC. SINTÉTICO'!$B:$B,0))} -> IMPERMEABILIZAÇÃO | E23: {=INDEX('ORC. SINTÉTICO'!$N:$N,MATCH($B23,'ORC. SINTÉTICO'!$B:$B,0))} -> 0 | F23: =IFERROR(E23/$E$41,"-") -> -
B24: 8 | C24: {=INDEX('ORC. SINTÉTICO'!$E:$E,MATCH($B24,'ORC. SINTÉTICO'!$B:$B,0))} -> REVESTIMENTO DE PAREDE | E24: {=INDEX('ORC. SINTÉTICO'!$N:$N,MATCH($B24,'ORC. SINTÉTICO'!$B:$B,0))} -> 0 | F24: =IFERROR(E24/$E$41,"-") -> -
B25: 9 | C25: {=INDEX('ORC. SINTÉTICO'!$E:$E,MATCH($B25,'ORC. SINTÉTICO'!$B:$B,0))} -> REVESTIMENTO DE PISO INTERNO | E25: {=INDEX('ORC. SINTÉTICO'!$N:$N,MATCH($B25,'ORC. SINTÉTICO'!$B:$B,0))} -> 0 | F25: =IFERROR(E25/$E$41,"-") -> -
B26: 10 | C26: {=INDEX('ORC. SINTÉTICO'!$E:$E,MATCH($B26,'ORC. SINTÉTICO'!$B:$B,0))} -> REVESTIMENTO DE PISO EXTERNO | E26: {=INDEX('ORC. SINTÉTICO'!$N:$N,MATCH($B26,'ORC. SINTÉTICO'!$B:$B,0))} -> 0 | F26: =IFERROR(E26/$E$41,"-") -> -
B27: 11 | C27: {=INDEX('ORC. SINTÉTICO'!$E:$E,MATCH($B27,'ORC. SINTÉTICO'!$B:$B,0))} -> REVESTIMENTO DE TETO | E27: {=INDEX('ORC. SINTÉTICO'!$N:$N,MATCH($B27,'ORC. SINTÉTICO'!$B:$B,0))} -> 0 | F27: =IFERROR(E27/$E$41,"-") -> -
B28: 12 | C28: {=INDEX('ORC. SINTÉTICO'!$E:$E,MATCH($B28,'ORC. SINTÉTICO'!$B:$B,0))} -> FACHADA | E28: {=INDEX('ORC. SINTÉTICO'!$N:$N,MATCH($B28,'ORC. SINTÉTICO'!$B:$B,0))} -> 0 | F28: =IFERROR(E28/$E$41,"-") -> -
... B39: 23 | C39: {=INDEX('ORC. SINTÉTICO'!$E:$E,MATCH($B39,'ORC. SINTÉTICO'!$B:$B,0))} -> SERVIÇOS COMPLEMENTARES | E39: {=INDEX('ORC. SINTÉTICO'!$N:$N,MATCH($B39,'ORC. SINTÉTICO'!$B:$B,0))} -> 0 | F39: =IFERROR(E39/$E$41,"-") -> -
B41: TOTAL | E41: =SUBTOTAL(9,E17:E39) -> 0 | F41: =SUBTOTAL(9,F17:F39) -> 0
B43: Notas:
B44: Estão exclusos do escopo: Calçada externa, piso intertravado, administração local, movimentação de terra, bate-macas, protetores de parede e portas, pingadeiras, mobiliário e equipamentos.
B51: ________________________________________________________________________________
B52: ='DADOS GERAIS'!C24 -> Thaís Ferreira Pellaquim
B53: ='DADOS GERAIS'!C25 -> Engenheira Civil - CREA MG 247749/D

Sheet ORC. SINTÉTICO
B2: PLANILHA DE ORÇAMENTO SINTÉTICO
B8: ='DADOS GERAIS'!$B$8 -> Secretaria de Atenção Especializada à Saúde | K8: =RESUMO!D8 -> BDI Geral: | M8: =RESUMO!E8 -> Encargo Social Mensalista: | O8: ='DADOS GERAIS'!$B$22 -> Data:
B9: ='DADOS GERAIS'!$B$9 -> Policlínica - Área Construída: 3.213,00 m² | K9: =RESUMO!D9 -> 0.24875249 | M9: =RESUMO!E9 -> 0.4757 | O9: ='DADOS GERAIS'!$C$22 -> 09/05/2024
B11: =RESUMO!B11 -> Bancos: | K11: =RESUMO!D11 -> BDI Equipamentos: | M11: =RESUMO!E11 -> Encargo Social Horista: | O11: ='DADOS GERAIS'!$B$23 -> Revisão:
B12: ='DADOS GERAIS'!$B$12 -> SINAPI (11/2023) - CPOS/CDHU (11/2023) - SBC (11/2023) - ORSE (11/2023) - SEINFRA (028) - IOPES (11/2023) - CAERN (11/2023) - EMOP (11/2023) | K12: =RESUMO!D12 -> 0.16857591 | M12: =RESUMO!E12 -> 0.8555518 | O12: ='DADOS GERAIS'!$C$23 -> 03
B15: Item | C15: Código | D15: Banco | E15: Descrição | F15: Und | G15: Quant. | H15: Valor Unit | I15: Valor Unit com BDI | L15: Total | O15: Peso (%)
I16: M. O. | J16: MAT. | K16: Total | L16: M. O. | M16: MAT. | N16: Total
B18: 1 | E18: SERVIÇOS PRELIMINARES E INDIRETOS
B19: 1.1 | E19: CANTEIRO DE OBRAS
B20: 1.1.1 | C20: 02.02.150 | D20: CPOS/CDHU | E20: LOCAÇÃO DE CONTAINER TIPO DEPÓSITO - ÁREA MÍNIMA DE 13,80 M² | F20: unxmês | G20: 32
B21: 1.1.2 | C21: 93582 | D21: SINAPI | E21: EXECUÇÃO DE CENTRAL DE ARMADURA EM CANTEIRO DE OBRA, NÃO INCLUSO MOBILIÁRIO E EQUIPAMENTOS. AF_04/2016 | F21: m² | G21: 14
B22: 1.1.3 | C22: 93583 | D22: SINAPI | E22: EXECUÇÃO DE CENTRAL DE FÔRMAS, PRODUÇÃO DE ARGAMASSA OU CONCRETO EM CANTEIRO DE OBRA, NÃO INCLUSO MOBILIÁRIO E EQUIPAMENTOS. AF_04/2016 | F22: m² | G22: 14
B23: 1.1.4 | C23: 02.02.130 | D23: CPOS/CDHU | E23: LOCAÇÃO DE CONTAINER TIPO ESCRITÓRIO COM 1 VASO SANITÁRIO, 1 LAVATÓRIO E 1 PONTO PARA CHUVEIRO - ÁREA MÍNIMA DE 13,80 M² | F23: unxmês | G23: 16
B24: 1.1.5 | C24: 02.02.160 | D24: CPOS/CDHU | E24: LOCAÇÃO DE CONTAINER TIPO GUARITA - ÁREA MÍNIMA DE 4,60 M² | F24: unxmês | G24: 16
B25: 1.1.6 | C25: 93210 | D25: SINAPI | E25: EXECUÇÃO DE REFEITÓRIO EM CANTEIRO DE OBRA EM CHAPA DE MADEIRA COMPENSADA, NÃO INCLUSO MOBILIÁRIO E EQUIPAMENTOS. AF_02/2016 | F25: m² | G25: 90
B26: 1.1.7 | C26: 02.02.140 | D26: CPOS/CDHU | E26: LOCAÇÃO DE CONTAINER TIPO SANITÁRIO COM 2 VASOS SANITÁRIOS, 2 LAVATÓRIOS, 2 MICTÓRIOS E 4 PONTOS PARA CHUVEIRO - ÁREA MÍNIMA DE 13,80 M² | F26: unxmês | G26: 64
B27: 1.1.8 | C27: 95648 | D27: SINAPI | E27: KIT CAVALETE PARA MEDIÇÃO DE ÁGUA - ENTRADA INDIVIDUALIZADA, EM CPVC DN 28 (1"), PARA 1 MEDIDOR - FORNECIMENTO E INSTALAÇÃO (EXCLUSIVE HIDRÔMETRO). AF_11/2016 | F27: UN | G27: 1
B28: 1.1.9 | C28: 95673 | D28: SINAPI | E28: HIDRÔMETRO DN 20 (½), 1,5 M³/H  FORNECIMENTO E INSTALAÇÃO. AF_11/2016 | F28: UN | G28: 1
B29: 1.1.10 | C29: 101509 | D29: SINAPI | E29: ENTRADA DE ENERGIA ELÉTRICA, AÉREA, TRIFÁSICA, COM CAIXA DE EMBUTIR, CABO DE 10 MM2 E DISJUNTOR DIN 50A (NÃO INCLUSO O POSTE DE CONCRETO). AF_07/2020_PS | F29: UN | G29: 1
B30: 1.1.11 | C30: 103689 | D30: SINAPI | E30: FORNECIMENTO E INSTALAÇÃO DE PLACA DE OBRA COM CHAPA GALVANIZADA E ESTRUTURA DE MADEIRA. AF_03/2022_PS | F30: m² | G30: 6
B31: 1.1.12 | C31: 93214 | D31: SINAPI | E31: EXECUÇÃO DE RESERVATÓRIO ELEVADO DE ÁGUA (1000 LITROS) EM CANTEIRO DE OBRA, APOIADO EM ESTRUTURA DE MADEIRA. AF_02/2016_PA | F31: UN | G31: 1
... B33: 1.1.14 | C33: 98459 | D33: SINAPI | E33: TAPUME COM TELHA METÁLICA. AF_05/2018 | F33: m² | G33: 640
B34: 1.2 | E34: MOBILIZAÇÃO E DESMOBILIZAÇÃO
B35: 1.2.1 | C35: 012689 | D35: SBC | E35: MOBILIZACAO E DESMOBILIZACAO DE CANTEIRO | F35: UN | G35: 1
B36: 1.2.2 | C36: 021101 | D36: SBC | E36: MOBILIZACAO/DESMOBILIZACAO DE EQUIP. E MO | F36: UN | G36: 1
B37: 1.3 | E37: EQUIPAMENTOS DE APOIO
B38: 1.3.1 | C38: CPU1926 | D38: Próprio | E38: LOCACAO DE ANDAIME METALICO TIPO FACHADEIRO, PECAS COM APROXIMADAMENTE 1,20 M DE LARGURA E 2,0 M DE ALTURA, INCLUINDO DIAGONAIS EM X, BARRAS DE LIGACAO, SAPATAS E DEMAIS ITENS NECESSARIOS A MONTAGEM, INCLUSIVE MONTAGEM E DESMONTAGEM | F38: M2XMÊS | G38: 5405.4
B39: 1.4 | E39: ADMINISTRAÇÃO LOCAL
B40: 1.4.1 | C40: 93565 | D40: SINAPI | E40: ENGENHEIRO CIVIL DE OBRA JUNIOR COM ENCARGOS COMPLEMENTARES | F40: MES | G40: 13
B41: 1.4.2 | C41: 93572 | D41: SINAPI | E41: ENCARREGADO GERAL DE OBRAS COM ENCARGOS COMPLEMENTARES | F41: MES | G41: 16
B42: 1.4.3 | C42: 101460 | D42: SINAPI | E42: VIGIA DIURNO COM ENCARGOS COMPLEMENTARES | F42: MES | G42: 16
B43: 1.4.4 | C43: 88326 | D43: SINAPI | E43: VIGIA NOTURNO COM ENCARGOS COMPLEMENTARES | F43: H | G43: 2560
B44: 2 | E44: FUNDAÇÃO
B45: 2.1 | C45: 99059 | D45: SINAPI | E45: LOCACAO CONVENCIONAL DE OBRA, UTILIZANDO GABARITO DE TÁBUAS CORRIDAS PONTALETADAS A CADA 2,00M - 2 UTILIZAÇÕES. AF_10/2018 | F45: M | G45: 224.5
B46: 2.2 | C46: 93358 | D46: SINAPI | E46: ESCAVAÇÃO MANUAL DE VALA COM PROFUNDIDADE MENOR OU IGUAL A 1,30 M. AF_02/2021 | F46: m³ | G46: 1314.95
B47: 2.3 | C47: 100324 | D47: SINAPI | E47: LASTRO COM MATERIAL GRANULAR (PEDRA BRITADA N.1 E PEDRA BRITADA N.2), APLICADO EM PISOS OU LAJES SOBRE SOLO, ESPESSURA DE *10 CM*. AF_07/2019 | F47: m³ | G47: 224.427
B48: 2.4 | C48: 96540 | D48: SINAPI | E48: FABRICAÇÃO, MONTAGEM E DESMONTAGEM DE FÔRMA PARA BLOCO DE COROAMENTO, EM CHAPA DE MADEIRA COMPENSADA RESINADA, E=17 MM, 4 UTILIZAÇÕES. AF_06/2017 | F48: m² | G48: 1709.7
B49: 2.5 | C49: 96543 | D49: SINAPI | E49: ARMAÇÃO DE BLOCO, VIGA BALDRAME E SAPATA UTILIZANDO AÇO CA-60 DE 5 MM - MONTAGEM. AF_06/2017 | F49: KG | G49: 1848.4
B50: 2.6 | C50: 96544 | D50: SINAPI | E50: ARMAÇÃO DE BLOCO, VIGA BALDRAME OU SAPATA UTILIZANDO AÇO CA-50 DE 6,3 MM - MONTAGEM. AF_06/2017 | F50: KG | G50: 14.8
B51: 2.7 | C51: 96545 | D51: SINAPI | E51: ARMAÇÃO DE BLOCO, VIGA BALDRAME OU SAPATA UTILIZANDO AÇO CA-50 DE 8 MM - MONTAGEM. AF_06/2017 | F51: KG | G51: 5867.6
B52: 2.8 | C52: 96546 | D52: SINAPI | E52: ARMAÇÃO DE BLOCO, VIGA BALDRAME OU SAPATA UTILIZANDO AÇO CA-50 DE 10 MM - MONTAGEM. AF_06/2017 | F52: KG | G52: 6726.3
B53: 2.9 | C53: 96547 | D53: SINAPI | E53: ARMAÇÃO DE BLOCO, VIGA BALDRAME OU SAPATA UTILIZANDO AÇO CA-50 DE 12,5 MM - MONTAGEM. AF_06/2017 | F53: KG | G53: 418
B54: 2.10 | C54: 96548 | D54: SINAPI | E54: ARMAÇÃO DE BLOCO, VIGA BALDRAME OU SAPATA UTILIZANDO AÇO CA-50 DE 16 MM - MONTAGEM. AF_06/2017 | F54: KG | G54: 506.5
B55: 2.11 | C55: CPU2096 | D55: Próprio | E55: CONCRETAGEM DE BLOCOS DE COROAMENTO E VIGAS BALDRAMES, FCK 35 MPA, COM USO DE BOMBA  LANÇAMENTO, ADENSAMENTO E ACABAMENTO | F55: m³ | G55: 277.9
B56: 2.12 | C56: 100574 | D56: SINAPI | E56: ESPALHAMENTO DE MATERIAL COM TRATOR DE ESTEIRAS. AF_11/2019 | F56: m³ | G56: 1178.382
... B59: 2.15 | C59: 000128 | D59: SBC | E59: CONTROLE TECNOLOGICO DE CONCRETOS | F59: m³ | G59: 277.9
B60: 3 | E60: ESTRUTURA
B61: 3.1 | E61: PILARES
B62: 3.1.1 | C62: 92423 | D62: SINAPI | E62: MONTAGEM E DESMONTAGEM DE FÔRMA DE PILARES RETANGULARES E ESTRUTURAS SIMILARES, PÉ-DIREITO SIMPLES, EM CHAPA DE MADEIRA COMPENSADA RESINADA, 6 UTILIZAÇÕES. AF_09/2020 | F62: m² | G62: 1329.2
B63: 3.1.2 | C63: 92760 | D63: SINAPI | E63: ARMAÇÃO DE PILAR OU VIGA DE ESTRUTURA CONVENCIONAL DE CONCRETO ARMADO UTILIZANDO AÇO CA-50 DE 6,3 MM - MONTAGEM. AF_06/2022 | F63: KG | G63: 41.7
B64: 3.1.3 | C64: 92762 | D64: SINAPI | E64: ARMAÇÃO DE PILAR OU VIGA DE ESTRUTURA CONVENCIONAL DE CONCRETO ARMADO UTILIZANDO AÇO CA-50 DE 10,0 MM - MONTAGEM. AF_06/2022 | F64: KG | G64: 4162.7
B65: 3.1.4 | C65: 92763 | D65: SINAPI | E65: ARMAÇÃO DE PILAR OU VIGA DE ESTRUTURA CONVENCIONAL DE CONCRETO ARMADO UTILIZANDO AÇO CA-50 DE 12,5 MM - MONTAGEM. AF_06/2022 | F65: KG | G65: 750.3
B66: 3.1.5 | C66: 92764 | D66: SINAPI | E66: ARMAÇÃO DE PILAR OU VIGA DE ESTRUTURA CONVENCIONAL DE CONCRETO ARMADO UTILIZANDO AÇO CA-50 DE 16,0 MM - MONTAGEM. AF_06/2022 | F66: KG | G66: 451.6
B67: 3.1.6 | C67: 92765 | D67: SINAPI | E67: ARMAÇÃO DE PILAR OU VIGA DE ESTRUTURA CONVENCIONAL DE CONCRETO ARMADO UTILIZANDO AÇO CA-50 DE 20,0 MM - MONTAGEM. AF_06/2022 | F67: KG | G67: 71.1
B68: 3.1.7 | C68: 92759 | D68: SINAPI | E68: ARMAÇÃO DE PILAR OU VIGA DE ESTRUTURA CONVENCIONAL DE CONCRETO ARMADO UTILIZANDO AÇO CA-60 DE 5,0 MM - MONTAGEM. AF_06/2022 | F68: KG | G68: 1762.6
B69: 3.1.8 | C69: CPU2097 | D69: Próprio | E69: CONCRETAGEM DE PILARES, FCK = 35 MPA, COM USO DE BOMBA - LANÇAMENTO, ADENSAMENTO E ACABAMENTO. AF_02/2022_PS | F69: m³ | G69: 82.7
B70: 3.1.9 | C70: 000128 | D70: SBC | E70: CONTROLE TECNOLOGICO DE CONCRETOS | F70: m³ | G70: 82.7
B71: 3.2 | E71: VIGAS
B72: 3.2.1 | C72: 92460 | D72: SINAPI | E72: MONTAGEM E DESMONTAGEM DE FÔRMA DE VIGA, ESCORAMENTO METÁLICO, PÉ-DIREITO SIMPLES, EM CHAPA DE MADEIRA RESINADA, 6 UTILIZAÇÕES. AF_09/2020 | F72: m² | G72: 1821.8
B73: 3.2.2 | C73: 92760 | D73: SINAPI | E73: ARMAÇÃO DE PILAR OU VIGA DE ESTRUTURA CONVENCIONAL DE CONCRETO ARMADO UTILIZANDO AÇO CA-50 DE 6,3 MM - MONTAGEM. AF_06/2022 | F73: KG | G73: 1238
B74: 3.2.3 | C74: 92761 | D74: SINAPI | E74: ARMAÇÃO DE PILAR OU VIGA DE ESTRUTURA CONVENCIONAL DE CONCRETO ARMADO UTILIZANDO AÇO CA-50 DE 8,0 MM - MONTAGEM. AF_06/2022 | F74: KG | G74: 1354.3
B75: 3.2.4 | C75: 92762 | D75: SINAPI | E75: ARMAÇÃO DE PILAR OU VIGA DE ESTRUTURA CONVENCIONAL DE CONCRETO ARMADO UTILIZANDO AÇO CA-50 DE 10,0 MM - MONTAGEM. AF_06/2022 | F75: KG | G75: 4375
B76: 3.2.5 | C76: 92763 | D76: SINAPI | E76: ARMAÇÃO DE PILAR OU VIGA DE ESTRUTURA CONVENCIONAL DE CONCRETO ARMADO UTILIZANDO AÇO CA-50 DE 12,5 MM - MONTAGEM. AF_06/2022 | F76: KG | G76: 3134.6
B77: 3.2.6 | C77: 92764 | D77: SINAPI | E77: ARMAÇÃO DE PILAR OU VIGA DE ESTRUTURA CONVENCIONAL DE CONCRETO ARMADO UTILIZANDO AÇO CA-50 DE 16,0 MM - MONTAGEM. AF_06/2022 | F77: KG | G77: 3063.3
B78: 3.2.7 | C78: 92765 | D78: SINAPI | E78: ARMAÇÃO DE PILAR OU VIGA DE ESTRUTURA CONVENCIONAL DE CONCRETO ARMADO UTILIZANDO AÇO CA-50 DE 20,0 MM - MONTAGEM. AF_06/2022 | F78: KG | G78: 888.6
B79: 3.2.8 | C79: 92759 | D79: SINAPI | E79: ARMAÇÃO DE PILAR OU VIGA DE ESTRUTURA CONVENCIONAL DE CONCRETO ARMADO UTILIZANDO AÇO CA-60 DE 5,0 MM - MONTAGEM. AF_06/2022 | F79: KG | G79: 2812.5
B80: 3.2.9 | C80: CPU2098 | D80: Próprio | E80: CONCRETAGEM DE LAJES EM EDIFICAÇÕES MULTIFAMILIARES FEITAS COM SISTEMA DE FÔRMAS MANUSEÁVEIS, COM CONCRETO USINADO BOMBEÁVEL FCK 35 MPA - LANÇAMENTO, ADENSAMENTO E ACABAMENTO. AF_10/2021 | F80: m³ | G80: 186.5
B81: 3.2.10 | C81: 000128 | D81: SBC | E81: CONTROLE TECNOLOGICO DE CONCRETOS | F81: m³ | G81: 186.5
B82: 3.3 | E82: LAJE E ESCADA
B83: 3.3.1 | C83: 92267 | D83: SINAPI | E83: FABRICAÇÃO DE FÔRMA PARA LAJES, EM CHAPA DE MADEIRA COMPENSADA RESINADA, E = 17 MM. AF_09/2020 | F83: m² | G83: 362.5
B84: 3.3.2 | C84: 102040 | D84: SINAPI | E84: MONTAGEM E DESMONTAGEM DE FÔRMA PARA ESCADAS, COM 1 LANCE E LAJE PLANA, EM MADEIRA SERRADA, 2 UTILIZAÇÕES. AF_11/2020 | F84: m² | G84: 33.3
B85: 3.3.3 | C85: CPU2098 | D85: Próprio | E85: CONCRETAGEM DE LAJES EM EDIFICAÇÕES MULTIFAMILIARES FEITAS COM SISTEMA DE FÔRMAS MANUSEÁVEIS, COM CONCRETO USINADO BOMBEÁVEL FCK 35 MPA - LANÇAMENTO, ADENSAMENTO E ACABAMENTO. AF_10/2021 | F85: m³ | G85: 271.6
B86: 3.3.4 | C86: 92768 | D86: SINAPI | E86: ARMAÇÃO DE LAJE DE ESTRUTURA CONVENCIONAL DE CONCRETO ARMADO UTILIZANDO AÇO CA-60 DE 5,0 MM - MONTAGEM. AF_06/2022 | F86: KG | G86: 451.7
B87: 3.3.5 | C87: 92769 | D87: SINAPI | E87: ARMAÇÃO DE LAJE DE ESTRUTURA CONVENCIONAL DE CONCRETO ARMADO UTILIZANDO AÇO CA-50 DE 6,3 MM - MONTAGEM. AF_06/2022 | F87: KG | G87: 623.8
B88: 3.3.6 | C88: 92770 | D88: SINAPI | E88: ARMAÇÃO DE LAJE DE ESTRUTURA CONVENCIONAL DE CONCRETO ARMADO UTILIZANDO AÇO CA-50 DE 8,0 MM - MONTAGEM. AF_06/2022 | F88: KG | G88: 2585.1
B89: 3.3.7 | C89: 92771 | D89: SINAPI | E89: ARMAÇÃO DE LAJE DE ESTRUTURA CONVENCIONAL DE CONCRETO ARMADO UTILIZANDO AÇO CA-50 DE 10,0 MM - MONTAGEM. AF_06/2022 | F89: KG | G89: 2502.6
B90: 3.3.8 | C90: 92772 | D90: SINAPI | E90: ARMAÇÃO DE LAJE DE ESTRUTURA CONVENCIONAL DE CONCRETO ARMADO UTILIZANDO AÇO CA-50 DE 12,5 MM - MONTAGEM. AF_06/2022 | F90: KG | G90: 970.5
B91: 3.3.9 | C91: 000128 | D91: SBC | E91: CONTROLE TECNOLOGICO DE CONCRETOS | F91: m³ | G91: 271.6
B92: 3.3.10 | C92: CPU2100 | D92: Próprio | E92: Laje pré-fabricada unidirecional em viga treliçada/lajota em EPS LT 16 (12 + 4), exceto capa de concreto | F92: m² | G92: 1711.14
B93: 3.3.11 | C93: CPU2101 | D93: Próprio | E93: Laje pré-fabricada unidirecional em viga treliçada/lajota em EPS LT 12 (8 + 4), exceto capa de concreto | F93: m² | G93: 79.15
B94: 3.3.12 | C94: CPU2102 | D94: Próprio | E94: Laje pré-fabricada unidirecional em viga treliçada/lajota em EPS LT 20 (16 + 4), exceto capa de concreto | F94: m² | G94: 1107.1
... B97: 3.3.15 | C97: 101792 | D97: SINAPI | E97: ESCORAMENTO DE FÔRMAS DE LAJE EM MADEIRA NÃO APARELHADA, PÉ-DIREITO SIMPLES, INCLUSO TRAVAMENTO, 4 UTILIZAÇÕES. AF_09/2020 | F97: m³ | G97: 10651.65
B98: 3.4 | E98: BASE RESERVATÓRIO
B99: 3.4.1 | C99: 97103 | D99: SINAPI | E99: EXECUÇÃO DE RADIER, ESPESSURA DE 20 CM, FCK = 30 MPA, COM USO DE FORMAS EM MADEIRA SERRADA. AF_09/2021 | F99: m² | G99: 6.25
B100: 4 | E100: ALVENARIA, VEDAÇÕES E DIVISÓRIAS
B101: 4.1 | E101: ALVENARIA DE VEDAÇÃO
B102: 4.1.1 | C102: 103336 | D102: SINAPI | E102: ALVENARIA DE VEDAÇÃO DE BLOCOS VAZADOS DE CONCRETO APARENTE DE 9X19X39 CM (ESPESSURA 9 CM) E ARGAMASSA DE ASSENTAMENTO COM PREPARO EM BETONEIRA. AF_12/2021 | F102: m² | G102: 179.01
B103: 4.1.2 | C103: 103318 | D103: SINAPI | E103: ALVENARIA DE VEDAÇÃO DE BLOCOS VAZADOS DE CONCRETO DE 14X19X39 CM (ESPESSURA 14 CM) E ARGAMASSA DE ASSENTAMENTO COM PREPARO EM BETONEIRA. AF_12/2021 | F103: m² | G103: 3654.44
B104: 4.1.3 | C104: 101161 | D104: SINAPI | E104: ALVENARIA DE VEDAÇÃO COM ELEMENTO VAZADO DE CONCRETO (COBOGÓ) DE 7X50X50CM E ARGAMASSA DE ASSENTAMENTO COM PREPARO EM BETONEIRA. AF_05/2020 | F104: m² | G104: 7.931
B105: 4.1.4 | C105: 93191 | D105: SINAPI | E105: VERGA MOLDADA IN LOCO COM UTILIZAÇÃO DE BLOCOS CANALETA PARA JANELAS COM MAIS DE 1,5 M DE VÃO. AF_03/2016 | F105: M | G105: 310.8
B106: 4.1.5 | C106: 93199 | D106: SINAPI | E106: CONTRAVERGA MOLDADA IN LOCO COM UTILIZAÇÃO DE BLOCOS CANALETA PARA VÃOS DE MAIS DE 1,5 M DE COMPRIMENTO. AF_03/2016 | F106: M | G106: 257.8
B107: 4.1.6 | C107: 93201 | D107: SINAPI | E107: FIXAÇÃO (ENCUNHAMENTO) DE ALVENARIA DE VEDAÇÃO COM ARGAMASSA APLICADA COM COLHER. AF_03/2016 | F107: M | G107: 1483.69
B108: 4.2 | E108: VEDAÇÃO DE DRYWALL
B109: 4.2.1 | C109: 96359 | D109: SINAPI | E109: PAREDE COM SISTEMA EM CHAPAS DE GESSO PARA DRYWALL, USO INTERNO, COM DUAS FACES SIMPLES E ESTRUTURA METÁLICA COM GUIAS SIMPLES PARA PAREDES COM ÁREA LÍQUIDA MAIOR OU IGUAL A 6 M2, COM VÃOS. AF_07/2023_PS | F109: m² | G109: 2091.94
B110: 4.2.2 | C110: CPU1942 | D110: Próprio | E110: PAREDE COM SISTEMA EM CHAPAS DE GESSO RU PARA DRYWALL, USO INTERNO, COM DUAS FACES SIMPLES E ESTRUTURA METÁLICA COM GUIAS SIMPLES PARA PAREDES COM ÁREA LÍQUIDA MAIOR OU IGUAL A 6 M2, COM VÃOS. AF_07/2023_PS | F110: m² | G110: 1861.56
B111: 4.2.3 | C111: CPU1943 | D111: Próprio | E111: PAREDE COM PLACAS DE GESSO ACARTONADO ST/ST (DRYWALL) COM REFORÇO METÁLICO PARA USO INTERNO, COM DUAS FACES DUPLAS E ESTRUTURA METÁLICA COM GUIAS SIMPLES, COM VÃOS. AF_06/2017_P | F111: m² | G111: 65.64
B112: 4.3 | E112: DIVISÓRIAS
B113: 4.3.1 | C113: 102257 | D113: SINAPI | E113: DIVISORIA SANITÁRIA, TIPO CABINE, EM PAINEL DE GRANILITE, ESP = 3CM, ASSENTADO COM ARGAMASSA COLANTE AC III-E, EXCLUSIVE FERRAGENS. AF_01/2021 | F113: m² | G113: 30.34
B114: 5 | E114: ESQUADRIAS
B115: 5.1 | E115: ESQUADRIAS DE MADEIRA
...

Sheet CPUS
B2: COMPOSIÇÕES ANALÍTICAS COM PREÇO UNITÁRIO
B8: ='DADOS GERAIS'!$B$8 -> Secretaria de Atenção Especializada à Saúde | G8: =RESUMO!D8 -> BDI Geral: | I8: =RESUMO!E8 -> Encargo Social Mensalista: | K8: ='DADOS GERAIS'!$B$22 -> Data:
B9: ='DADOS GERAIS'!$B$9 -> Policlínica - Área Construída: 3.213,00 m² | G9: =RESUMO!D9 -> 0.24875249 | I9: =RESUMO!E9 -> 0.4757 | K9: ='DADOS GERAIS'!$C$22 -> 09/05/2024
B11: =RESUMO!B11 -> Bancos: | G11: =RESUMO!D11 -> BDI Equipamentos: | I11: =RESUMO!E11 -> Encargo Social Horista: | K11: ='DADOS GERAIS'!$B$23 -> Revisão:
B12: ='DADOS GERAIS'!$B$12 -> SINAPI (11/2023) - CPOS/CDHU (11/2023) - SBC (11/2023) - ORSE (11/2023) - SEINFRA (028) - IOPES (11/2023) - CAERN (11/2023) - EMOP (11/2023) | G12: =RESUMO!D12 -> 0.16857591 | I12: =RESUMO!E12 -> 0.8555518 | K12: ='DADOS GERAIS'!$C$23 -> 03
B15: Item | C15: Código | D15: Banco | E15: Descrição | G15: Und | H15: Quant. | I15: Porcent. | J15: Valor Unit | K15: Total
B17: Composições Principais
B18: 1.3.1 | C18: Código | D18: Banco | E18: Descrição | F18: Tipo | H18: Und | I18: Quant. | J18: Valor Unit | K18: Total
B19: Composição | C19: CPU1926 | D19: Próprio | E19: LOCACAO DE ANDAIME METALICO TIPO FACHADEIRO, PECAS COM APROXIMADAMENTE 1,20 M DE LARGURA E 2,0 M DE ALTURA, INCLUINDO DIAGONAIS EM X, BARRAS DE LIGACAO, SAPATAS E DEMAIS ITENS NECESSARIOS A MONTAGEM, INCLUSIVE MONTAGEM E DESMONTAGEM | F19: ASTU - ASSENTAMENTO DE TUBOS E PECAS | H19: M2XMÊS | I19: 1
B20: Composição Auxiliar | C20: 97063 | D20: SINAPI | E20: MONTAGEM E DESMONTAGEM DE ANDAIME MODULAR FACHADEIRO, COM PISO METÁLICO, PARA EDIFICAÇÕES COM MÚLTIPLOS PAVIMENTOS (EXCLUSIVE ANDAIME E LIMPEZA). AF_11/2017 | F20: SEDI - SERVIÇOS DIVERSOS | H20: m² | I20: 0.416
B21: Insumo | C21: 00020193 | D21: SINAPI | E21: LOCACAO DE ANDAIME METALICO TIPO FACHADEIRO, PECAS COM APROXIMADAMENTE 1,20 M DE LARGURA E 2,0 M DE ALTURA, INCLUINDO DIAGONAIS EM X, BARRAS DE LIGACAO, SAPATAS E DEMAIS ITENS NECESSARIOS A MONTAGEM (NAO INCLUI INSTALACAO) | F21: Equipamento | H21: M2/MES | I21: 1
F22: MO sem LS => | H22: LS => | I22: 0 | J22: MO com LS =>
F23: Valor do BDI => | I23: Valor com BDI =>
B25: 2.11 | C25: Código | D25: Banco | E25: Descrição | F25: Tipo | H25: Und | I25: Quant. | J25: Valor Unit | K25: Total
B26: Composição | C26: CPU2096 | D26: Próprio | E26: CONCRETAGEM DE BLOCOS DE COROAMENTO E VIGAS BALDRAMES, FCK 35 MPA, COM USO DE BOMBA  LANÇAMENTO, ADENSAMENTO E ACABAMENTO | F26: FUES - FUNDAÇÕES E ESTRUTURAS | H26: m³ | I26: 1
B27: Composição Auxiliar | C27: 90587 | D27: SINAPI | E27: VIBRADOR DE IMERSÃO, DIÂMETRO DE PONTEIRA 45MM, MOTOR ELÉTRICO TRIFÁSICO POTÊNCIA DE 2 CV - CHI DIURNO. AF_06/2015 | F27: CHOR - CUSTOS HORÁRIOS DE MÁQUINAS E EQUIPAMENTOS | H27: CHI | I27: 0.093
B28: Composição Auxiliar | C28: 88316 | D28: SINAPI | E28: SERVENTE COM ENCARGOS COMPLEMENTARES | F28: SEDI - SERVIÇOS DIVERSOS | H28: H | I28: 0.544
B29: Composição Auxiliar | C29: 88309 | D29: SINAPI | E29: PEDREIRO COM ENCARGOS COMPLEMENTARES | F29: SEDI - SERVIÇOS DIVERSOS | H29: H | I29: 0.363
B30: Composição Auxiliar | C30: 90586 | D30: SINAPI | E30: VIBRADOR DE IMERSÃO, DIÂMETRO DE PONTEIRA 45MM, MOTOR ELÉTRICO TRIFÁSICO POTÊNCIA DE 2 CV - CHP DIURNO. AF_06/2015 | F30: CHOR - CUSTOS HORÁRIOS DE MÁQUINAS E EQUIPAMENTOS | H30: CHP | I30: 0.088
B31: Insumo | C31: 00011145 | D31: SINAPI | E31: CONCRETO USINADO BOMBEAVEL, CLASSE DE RESISTENCIA C35, BRITA 0 E 1, SLUMP = 100 +/- 20 MM, COM BOMBEAMENTO (DISPONIBILIZACAO DE BOMBA), SEM O LANCAMENTO (NBR 8953) | F31: Material | H31: M³ | I31: 1.15
F32: MO sem LS => | H32: LS => | I32: 0 | J32: MO com LS =>
F33: Valor do BDI => | I33: Valor com BDI =>
B35: 3.1.8 | C35: Código | D35: Banco | E35: Descrição | F35: Tipo | H35: Und | I35: Quant. | J35: Valor Unit | K35: Total
B36: Composição | C36: CPU2097 | D36: Próprio | E36: CONCRETAGEM DE PILARES, FCK = 35 MPA, COM USO DE BOMBA - LANÇAMENTO, ADENSAMENTO E ACABAMENTO. AF_02/2022_PS | F36: FUES - FUNDAÇÕES E ESTRUTURAS | H36: m³ | I36: 1
B37: Composição Auxiliar | C37: 88309 | D37: SINAPI | E37: PEDREIRO COM ENCARGOS COMPLEMENTARES | F37: SEDI - SERVIÇOS DIVERSOS | H37: H | I37: 0.224
B38: Composição Auxiliar | C38: 90586 | D38: SINAPI | E38: VIBRADOR DE IMERSÃO, DIÂMETRO DE PONTEIRA 45MM, MOTOR ELÉTRICO TRIFÁSICO POTÊNCIA DE 2 CV - CHP DIURNO. AF_06/2015 | F38: CHOR - CUSTOS HORÁRIOS DE MÁQUINAS E EQUIPAMENTOS | H38: CHP | I38: 0.094
B39: Composição Auxiliar | C39: 90587 | D39: SINAPI | E39: VIBRADOR DE IMERSÃO, DIÂMETRO DE PONTEIRA 45MM, MOTOR ELÉTRICO TRIFÁSICO POTÊNCIA DE 2 CV - CHI DIURNO. AF_06/2015 | F39: CHOR - CUSTOS HORÁRIOS DE MÁQUINAS E EQUIPAMENTOS | H39: CHI | I39: 0.13
B40: Composição Auxiliar | C40: 88262 | D40: SINAPI | E40: CARPINTEIRO DE FORMAS COM ENCARGOS COMPLEMENTARES | F40: SEDI - SERVIÇOS DIVERSOS | H40: H | I40: 0.224
B41: Composição Auxiliar | C41: 88316 | D41: SINAPI | E41: SERVENTE COM ENCARGOS COMPLEMENTARES | F41: SEDI - SERVIÇOS DIVERSOS | H41: H | I41: 1.345
B42: Insumo | C42: 00011145 | D42: SINAPI | E42: CONCRETO USINADO BOMBEAVEL, CLASSE DE RESISTENCIA C35, BRITA 0 E 1, SLUMP = 100 +/- 20 MM, COM BOMBEAMENTO (DISPONIBILIZACAO DE BOMBA), SEM O LANCAMENTO (NBR 8953) | F42: Material | H42: M³ | I42: 1.103
F43: MO sem LS => | H43: LS => | I43: 0 | J43: MO com LS =>
F44: Valor do BDI => | I44: Valor com BDI =>
B46: 3.2.9 | C46: Código | D46: Banco | E46: Descrição | F46: Tipo | H46: Und | I46: Quant. | J46: Valor Unit | K46: Total
B47: Composição | C47: CPU2098 | D47: Próprio | E47: CONCRETAGEM DE LAJES EM EDIFICAÇÕES MULTIFAMILIARES FEITAS COM SISTEMA DE FÔRMAS MANUSEÁVEIS, COM CONCRETO USINADO BOMBEÁVEL FCK 35 MPA - LANÇAMENTO, ADENSAMENTO E ACABAMENTO. AF_10/2021 | F47: FUES - FUNDAÇÕES E ESTRUTURAS | H47: m³ | I47: 1
B48: Composição Auxiliar | C48: 88309 | D48: SINAPI | E48: PEDREIRO COM ENCARGOS COMPLEMENTARES | F48: SEDI - SERVIÇOS DIVERSOS | H48: H | I48: 0.556
B49: Composição Auxiliar | C49: 88262 | D49: SINAPI | E49: CARPINTEIRO DE FORMAS COM ENCARGOS COMPLEMENTARES | F49: SEDI - SERVIÇOS DIVERSOS | H49: H | I49: 0.139
B50: Composição Auxiliar | C50: 88316 | D50: SINAPI | E50: SERVENTE COM ENCARGOS COMPLEMENTARES | F50: SEDI - SERVIÇOS DIVERSOS | H50: H | I50: 0.626
B51: Composição Auxiliar | C51: 90587 | D51: SINAPI | E51: VIBRADOR DE IMERSÃO, DIÂMETRO DE PONTEIRA 45MM, MOTOR ELÉTRICO TRIFÁSICO POTÊNCIA DE 2 CV - CHI DIURNO. AF_06/2015 | F51: CHOR - CUSTOS HORÁRIOS DE MÁQUINAS E EQUIPAMENTOS | H51: CHI | I51: 0.071
B52: Composição Auxiliar | C52: 90586 | D52: SINAPI | E52: VIBRADOR DE IMERSÃO, DIÂMETRO DE PONTEIRA 45MM, MOTOR ELÉTRICO TRIFÁSICO POTÊNCIA DE 2 CV - CHP DIURNO. AF_06/2015 | F52: CHOR - CUSTOS HORÁRIOS DE MÁQUINAS E EQUIPAMENTOS | H52: CHP | I52: 0.068
B53: Insumo | C53: 00011145 | D53: SINAPI | E53: CONCRETO USINADO BOMBEAVEL, CLASSE DE RESISTENCIA C35, BRITA 0 E 1, SLUMP = 100 +/- 20 MM, COM BOMBEAMENTO (DISPONIBILIZACAO DE BOMBA), SEM O LANCAMENTO (NBR 8953) | F53: Material | H53: M³ | I53: 1.11
F54: MO sem LS => | H54: LS => | I54: 0 | J54: MO com LS =>
F55: Valor do BDI => | I55: Valor com BDI =>
B57: 3.3.10 | C57: Código | D57: Banco | E57: Descrição | F57: Tipo | H57: Und | I57: Quant. | J57: Valor Unit | K57: Total
B58: Composição | C58: CPU2100 | D58: Próprio | E58: Laje pré-fabricada unidirecional em viga treliçada/lajota em EPS LT 16 (12 + 4), exceto capa de concreto | F58: 13.01 | H58: m² | I58: 1
B59: Insumo | C59: C.06.000.022012 | D59: CPOS/CDHU | E59: LAJE PRÉ-FABRICADA UNIDIRECIONAL EM VIGA TRELIÇADA/LAJOTA EM EPS LT 16 (12 + 4) - SC = 300KGF/M² | F59: Material | H59: m² | I59: 1
B60: Insumo | C60: B.01.000.010139 | D60: CPOS/CDHU | E60: PEDREIRO | F60: Mão de Obra | H60: h | I60: 0.4
B61: Insumo | C61: B.01.000.010146 | D61: CPOS/CDHU | E61: SERVENTE | F61: Mão de Obra | H61: h | I61: 0.8
F62: MO sem LS => | H62: LS => | I62: 0 | J62: MO com LS =>
F63: Valor do BDI => | I63: Valor com BDI =>
B65: 3.3.11 | C65: Código | D65: Banco | E65: Descrição | F65: Tipo | H65: Und | I65: Quant. | J65: Valor Unit | K65: Total
B66: Composição | C66: CPU2101 | D66: Próprio | E66: Laje pré-fabricada unidirecional em viga treliçada/lajota em EPS LT 12 (8 + 4), exceto capa de concreto | F66: 13.01 | H66: m² | I66: 1
B67: Insumo | C67: C.06.000.022011 | D67: CPOS/CDHU | E67: LAJE PRÉ-FABRICADA UNIDIRECIONAL EM VIGA TRELIÇADA/LAJOTA EM EPS LT 12 (8 + 4) - SC = 200KGF/M² | F67: Material | H67: m² | I67: 1
B68: Insumo | C68: B.01.000.010146 | D68: CPOS/CDHU | E68: SERVENTE | F68: Mão de Obra | H68: h | I68: 0.8
B69: Insumo | C69: B.01.000.010139 | D69: CPOS/CDHU | E69: PEDREIRO | F69: Mão de Obra | H69: h | I69: 0.4
F70: MO sem LS => | H70: LS => | I70: 0 | J70: MO com LS =>
F71: Valor do BDI => | I71: Valor com BDI =>
B73: 3.3.12 | C73: Código | D73: Banco | E73: Descrição | F73: Tipo | H73: Und | I73: Quant. | J73: Valor Unit | K73: Total
B74: Composição | C74: CPU2102 | D74: Próprio | E74: Laje pré-fabricada unidirecional em viga treliçada/lajota em EPS LT 20 (16 + 4), exceto capa de concreto | F74: 13.01 | H74: m² | I74: 1
B75: Insumo | C75: B.01.000.010146 | D75: CPOS/CDHU | E75: SERVENTE | F75: Mão de Obra | H75: h | I75: 0.9
B76: Insumo | C76: B.01.000.010139 | D76: CPOS/CDHU | E76: PEDREIRO | F76: Mão de Obra | H76: h | I76: 0.45
B77: Insumo | C77: C.06.000.022013 | D77: CPOS/CDHU | E77: LAJE PRÉ-FABRICADA UNIDIRECIONAL EM VIGA TRELIÇADA/LAJOTA EM EPS LT 20 (16 + 4) - SC = 300KGF/M² | F77: Material | H77: m² | I77: 1
F78: MO sem LS => | H78: LS => | I78: 0 | J78: MO com LS =>
F79: Valor do BDI => | I79: Valor com BDI =>
B81: 3.3.13 | C81: Código | D81: Banco | E81: Descrição | F81: Tipo | H81: Und | I81: Quant. | J81: Valor Unit | K81: Total
B82: Composição | C82: CPU2103 | D82: Próprio | E82: Laje pré-fabricada unidirecional em viga treliçada/lajota em EPS LT 25 (20 + 5), exceto capa de concreto | F82: 13.01 | H82: m² | I82: 1
B83: Insumo | C83: B.01.000.010139 | D83: CPOS/CDHU | E83: PEDREIRO | F83: Mão de Obra | H83: h | I83: 0.5
B84: Insumo | C84: B.01.000.010146 | D84: CPOS/CDHU | E84: SERVENTE | F84: Mão de Obra | H84: h | I84: 1
B85: Insumo | C85: C.06.000.022014 | D85: CPOS/CDHU | E85: LAJE PRÉ-FABRICADA UNIDIRECIONAL EM VIGA TRELIÇADA/LAJOTA EM EPS LT 25 (20 + 5) - SC = 300KGF/M² | F85: Material | H85: m² | I85: 1
F86: MO sem LS => | H86: LS => | I86: 0 | J86: MO com LS =>
F87: Valor do BDI => | I87: Valor com BDI =>
B89: 3.3.14 | C89: Código | D89: Banco | E89: Descrição | F89: Tipo | H89: Und | I89: Quant. | J89: Valor Unit | K89: Total
B90: Composição | C90: CPU2104 | D90: Próprio | E90: LAJE PRE-FABRICADA PRE-LAJE TRELICADA BIDIR C/ EPS PLT-16 300KGF/M2 | F90: 3.03 | H90: m² | I90: 1
B91: Composição Auxiliar | C91: 88316 | D91: SINAPI | E91: SERVENTE COM ENCARGOS COMPLEMENTARES | F91: SEDI - SERVIÇOS DIVERSOS | H91: H | I91: 1.12
B92: Composição Auxiliar | C92: 88309 | D92: SINAPI | E92: PEDREIRO COM ENCARGOS COMPLEMENTARES | F92: SEDI - SERVIÇOS DIVERSOS | H92: H | I92: 0.52
B93: Insumo | C93: 11949 | D93: ORSE | E93: Laje pré-fabricada treliçada para piso ou cobertura, bidirecional, h=30cm, el. enchimento em bloco EPS, h=25cm, inclusive ferragem adicional da treliça | F93: Material | H93: m² | I93: 0.64
F94: MO sem LS => | H94: LS => | I94: 0 | J94: MO com LS =>
F95: Valor do BDI => | I95: Valor com BDI =>
B97: 4.2.2 | C97: Código | D97: Banco | E97: Descrição | F97: Tipo | H97: Und | I97: Quant. | J97: Valor Unit | K97: Total
B98: Composição | C98: CPU1942 | D98: Próprio | E98: PAREDE COM SISTEMA EM CHAPAS DE GESSO RU PARA DRYWALL, USO INTERNO, COM DUAS FACES SIMPLES E ESTRUTURA METÁLICA COM GUIAS SIMPLES PARA PAREDES COM ÁREA LÍQUIDA MAIOR OU IGUAL A 6 M2, COM VÃOS. AF_07/2023_PS | F98: PARE - PAREDES/PAINEIS | H98: m² | I98: 1
B99: Composição Auxiliar | C99: 88278 | D99: SINAPI | E99: MONTADOR DE ESTRUTURA METÁLICA COM ENCARGOS COMPLEMENTARES | F99: SEDI - SERVIÇOS DIVERSOS | H99: H | I99: 0.595
B100: Composição Auxiliar | C100: 88316 | D100: SINAPI | E100: SERVENTE COM ENCARGOS COMPLEMENTARES | F100: SEDI - SERVIÇOS DIVERSOS | H100: H | I100: 0.195
B101: Insumo | C101: 00039432 | D101: SINAPI | E101: FITA DE PAPEL REFORCADA COM LAMINA DE METAL PARA REFORCO DE CANTOS DE CHAPA DE GESSO PARA DRYWALL | F101: Material | H101: M | I101: 0.7925
B102: Insumo | C102: 00037586 | D102: SINAPI | E102: PINO DE ACO COM ARRUELA CONICA, DIAMETRO ARRUELA = *23* MM E COMP HASTE = *27* MM (ACAO INDIRETA) | F102: Material | H102: CENTO | I102: 0.0296
B103: Insumo | C103: 00039417 | D103: SINAPI | E103: PLACA / CHAPA DE GESSO ACARTONADO, RESISTENTE A UMIDADE (RU), COR VERDE, E = 12,5 MM, 1200 X 2400 MM (L X C) | F103: Material | H103: m² | I103: 2.106
B104: Insumo | C104: 00039443 | D104: SINAPI | E104: PARAFUSO DRY WALL, EM ACO ZINCADO, CABECA LENTILHA E PONTA BROCA (LB), LARGURA 4,2 MM, COMPRIMENTO 13 MM | F104: Material | H104: UN | I104: 0.5441
B105: Insumo | C105: 00039419 | D105: SINAPI | E105: PERFIL GUIA, FORMATO U, EM ACO ZINCADO, PARA ESTRUTURA PAREDE DRYWALL, E = 0,5 MM, 70 X 3000 MM (L X C) | F105: Material | H105: M | I105: 0.9117
B106: Insumo | C106: 00039435 | D106: SINAPI | E106: PARAFUSO DRY WALL, EM ACO FOSFATIZADO, CABECA TROMBETA E PONTA AGULHA (TA), COMPRIMENTO 25 MM | F106: Material | H106: UN | I106: 20.1868
B107: Insumo | C107: 00039422 | D107: SINAPI | E107: PERFIL MONTANTE, FORMATO C, EM ACO ZINCADO, PARA ESTRUTURA PAREDE DRYWALL, E = 0,5 MM, 70 X 3000 MM (L X C) | F107: Material | H107: M | I107: 2.9139
B108: Insumo | C108: 00039431 | D108: SINAPI | E108: FITA DE PAPEL MICROPERFURADO, 50 X 150 MM, PARA TRATAMENTO DE JUNTAS DE CHAPA DE GESSO PARA DRYWALL | F108: Material | H108: M | I108: 2.5027
B109: Insumo | C109: 00039434 | D109: SINAPI | E109: MASSA DE REJUNTE EM PO PARA DRYWALL, A BASE DE GESSO, SECAGEM RAPIDA, PARA TRATAMENTO DE JUNTAS DE CHAPA DE GESSO (NECESSITA ADICAO DE AGUA) | F109: Equipamento | H109: KG | I109: 1.0978
F110: MO sem LS => | H110: LS => | I110: 0 | J110: MO com LS =>
F111: Valor do BDI => | I111: Valor com BDI =>
B113: 4.2.3 | C113: Código | D113: Banco | E113: Descrição | F113: Tipo | H113: Und | I113: Quant. | J113: Valor Unit | K113: Total
B114: Composição | C114: CPU1943 | D114: Próprio | E114: PAREDE COM PLACAS DE GESSO ACARTONADO ST/ST (DRYWALL) COM REFORÇO METÁLICO PARA USO INTERNO, COM DUAS FACES DUPLAS E ESTRUTURA METÁLICA COM GUIAS SIMPLES, COM VÃOS. AF_06/2017_P | F114: PARE - PAREDES/PAINEIS | H114: m² | I114: 1
B115: Composição Auxiliar | C115: 88278 | D115: SINAPI | E115: MONTADOR DE ESTRUTURA METÁLICA COM ENCARGOS COMPLEMENTARES | F115: SEDI - SERVIÇOS DIVERSOS | H115: H | I115: 0.8473
B116: Composição Auxiliar | C116: 88316 | D116: SINAPI | E116: SERVENTE COM ENCARGOS COMPLEMENTARES | F116: SEDI - SERVIÇOS DIVERSOS | H116: H | I116: 0.2118
B117: Composição Auxiliar | C117: 96373 | D117: SINAPI | E117: INSTALAÇÃO DE REFORÇO METÁLICO EM PAREDE DRYWALL. AF_07/2023 | F117: PARE - PAREDES/PAINEIS | H117: M | I117: 1.05
B118: Insumo | C118: 00039431 | D118: SINAPI | E118: FITA DE PAPEL MICROPERFURADO, 50 X 150 MM, PARA TRATAMENTO DE JUNTAS DE CHAPA DE GESSO PARA DRYWALL | F118: Material | H118: M | I118: 2.5027
B119: Insumo | C119: 00039423 | D119: SINAPI | E119: PERFIL MONTANTE, FORMATO C, EM ACO ZINCADO, PARA ESTRUTURA PAREDE DRYWALL, E = 0,5 MM, 90 X 3000 MM (L X C) | F119: Material | H119: M | I119: 2.8999
B120: Insumo | C120: 00037586 | D120: SINAPI | E120: PINO DE ACO COM ARRUELA CONICA, DIAMETRO ARRUELA = *23* MM E COMP HASTE = *27* MM (ACAO INDIRETA) | F120: Material | H120: CENTO | I120: 0.029
...

Sheet BDI DESONERADO
B2: BONIFICAÇÕES E DESPESAS INDIRETAS
B8: ='DADOS GERAIS'!B8 -> Secretaria de Atenção Especializada à Saúde | D8: BDI Geral: | E8: Encargo Social Mensalista: | F8: ='DADOS GERAIS'!$B$22 -> Data:
B9: ='DADOS GERAIS'!B9 -> Policlínica - Área Construída: 3.213,00 m² | D9: ='DADOS GERAIS'!C19 -> 0.24875249 | E9: ='ENCARGOS SOCIAIS'!F56 -> 0.4757 | F9: ='DADOS GERAIS'!$C$22 -> 09/05/2024
B11: ='DADOS GERAIS'!B11 -> Bancos: | D11: BDI Equipamentos: | E11: Encargo Social Horista: | F11: ='DADOS GERAIS'!$B$23 -> Revisão:
B12: ='DADOS GERAIS'!B12 -> SINAPI (11/2023) - CPOS/CDHU (11/2023) - SBC (11/2023) - ORSE (11/2023) - SEINFRA (028) - IOPES (11/2023) - CAERN (11/2023) - EMOP (11/2023) | D12: ='DADOS GERAIS'!C20 -> 0.16857591 | E12: ='ENCARGOS SOCIAIS'!E56 -> 0.8555518 | F12: ='DADOS GERAIS'!$C$23 -> 03
B15: Fórmula (Bonificações e Despesas Indiretas):
B22: ITEM | C22: DESCRIÇÃO | D22: CÓD | E22: GERAL VALORES PROPOSTOS (%) | F22: EQUIPAMENTOS VALORES PROPOSTOS (%)
B25: 1 | C25: Administração Central | D25: AC | E25: 0.03 | F25: 0.015
B26: 2 | C26: Riscos | D26: R | E26: 0.0127 | F26: 0.0085
B27: 3 | C27: Seguros e Garantias | D27: SG | E27: 0.008 | F27: 0.0048
B28: 4 | C28: Despesas Financeiras | D28: DF | E28: 0.0059 | F28: 0.0085
B29: 5 | C29: Lucro | D29: L | E29: 0.0616 | F29: 0.035
B30: 6 | C30: Impostos | D30: I | E30: =SUM(E31:E34) -> 0.1015 | F30: =SUM(F31:F34) -> 0.0815
B31: 6.1 | C31: PIS | E31: 0.0065 | F31: 0.0065
B32: 6.2 | C32: COFINS | E32: 0.03 | F32: 0.03
B33: 6.3 | C33: ISSQN | E33: 0.02 | F33: 0
B34: 6.4 | C34: CPRB | E34: 0.045 | F34: 0.045
B36: BDI | E36: =((1+E25+E26+E27)*(1+E28)*(1+E29)/(1-E30))-1 -> 0.24875249 | F36: =((1+F25+F26+F27)*(1+F28)*(1+F29)/(1-F30))-1 -> 0.16857591
B39: FONTE:
B40: 1. | C40: Tribunal de Contas da União - TC 036.076/2011-2 - Acórdão Nº 2622/2013
B41: 2. | C41: ISS conforme a Lei Complementar 116/2003 e a Lei 11.438/1997 da Prefeitura Municipal de São Paulo.
B42: 3. | C42: O valor do CPRB foi considerado baseado na Instrução Normativa nº 2053, de 6 de Dezembro de 2021, onde desde Dezembro de 2015 o percentual passa a ser 4,5% e não mais 2,0%. Essa recomendação aplica-se para orçamentos de Construção Civil para os enquadrados nos grupos 412, 432, 433 e 439 da CNAE 2.0. A edificação objeto desta composição se enquadra no grupo 412:4120-4/00 - CLINICAS, HOSPITAIS, CONSTRUÇÃO OU REFORMA.
B44: NOTAS:
B45: 1. | C45: Deverão ser obedecidas as legislações trabalhistas e tributária vigentes, inclusive acordos de classes, sob pena de desclassificação da Proposta de Preços;
B46: 2. | C46: É de responsabilidade da proponente a adequação de todas as fórmulas utilizadas na planilha orçamentária.
B48: ________________________________________________________________________________
B52: ='DADOS GERAIS'!C24 -> Thaís Ferreira Pellaquim
B53: ='DADOS GERAIS'!C25 -> Engenheira Civil - CREA MG 247749/D

Sheet ENCARGOS SOCIAIS
B2: COMPOSIÇÃO ANALÍTICA DAS TAXAS DE ENCARGOS SOCIAIS
B8: ='DADOS GERAIS'!B8 -> Secretaria de Atenção Especializada à Saúde | D8: BDI Geral: | E8: Encargo Social Mensalista: | F8: ='DADOS GERAIS'!$B$22 -> Data:
B9: ='DADOS GERAIS'!B9 -> Policlínica - Área Construída: 3.213,00 m² | D9: ='DADOS GERAIS'!C19 -> 0.24875249 | E9: ='ENCARGOS SOCIAIS'!F56 -> 0.4757 | F9: ='DADOS GERAIS'!$C$22 -> 09/05/2024
B11: ='DADOS GERAIS'!B11 -> Bancos: | D11: BDI Equipamentos: | E11: Encargo Social Horista: | F11: ='DADOS GERAIS'!$B$23 -> Revisão:
B12: ='DADOS GERAIS'!B12 -> SINAPI (11/2023) - CPOS/CDHU (11/2023) - SBC (11/2023) - ORSE (11/2023) - SEINFRA (028) - IOPES (11/2023) - CAERN (11/2023) - EMOP (11/2023) | D12: ='DADOS GERAIS'!C20 -> 0.16857591 | E12: ='ENCARGOS SOCIAIS'!E56 -> 0.8555518 | F12: ='DADOS GERAIS'!$C$23 -> 03
B15: ENCARGOS SOCIAIS SOBRE A MÃO DE OBRA
B16: CÓDIGO | C16: DESCRIÇÃO | E16: COM DESONERAÇÃO
E17: HORISTA (%) | F17: MENSALISTA (%)
B19: GRUPO A
B20: A1 | C20: INSS | E20: 0 | F20: 0
B21: A2 | C21: SESI | E21: 0.015 | F21: 0.015
B22: A3 | C22: SENAI | E22: 0.01 | F22: 0.01
B23: A4 | C23: INCRA | E23: 0.002 | F23: 0.002
B24: A5 | C24: SEBRAE | E24: 0.006 | F24: 0.006
B25: A6 | C25: Salário Educação | E25: 0.025 | F25: 0.025
B26: A7 | C26: Seguro Contra Acidentes de Trabalho | E26: 0.03 | F26: 0.03
B27: A8 | C27: FGTS | E27: 0.08 | F27: 0.08
B28: A9 | C28: SECONCI | E28: 0.01 | F28: 0.01
B29: A | C29: Total | E29: =SUBTOTAL(9,E20:E28) -> 0.178 | F29: =SUBTOTAL(9,F20:F28) -> 0.178
B31: GRUPO B
B32: B1 | C32: Repouso Semanal Remunerado | E32: 0.1798 | F32: Não incide
B33: B2 | C33: Feriados | E33: 0.0469 | F33: Não incide
B34: B3 | C34: Auxílio-Enfermidade | E34: 0.0087 | F34: 0.0066
B35: B4 | C35: 13º Salário | E35: 0.1104 | F35: 0.0833
B36: B5 | C36: Licença Paternidade | E36: 0.0007 | F36: 0.0005
B37: B6 | C37: Faltas Justificadas | E37: 0.0074 | F37: 0.0056
B38: B7 | C38: Dias de Chuva | E38: 0.0135 | F38: Não incide
B39: B8 | C39: Auxílo Acidente de Trabalho | E39: 0.0011 | F39: 0.0008
B40: B9 | C40: Férias Gozadas | E40: 0.1151 | F40: 0.0868
B41: B10 | C41: Salário Maternidade | E41: 0.0004 | F41: 0.0003
B42: B | C42: Total | E42: =SUBTOTAL(9,E32:E41) -> 0.484 | F42: =SUBTOTAL(9,F32:F41) -> 0.1839
B44: GRUPO C
B45: C1 | C45: Aviso Prévio Indenizado | E45: 0.0482 | F45: 0.0364
B46: C2 | C46: Aviso Prévio Trabalhado | E46: 0.0011 | F46: 0.0009
B47: C3 | C47: Férias Indenizadas | E47: 0.0229 | F47: 0.0173
B48: C4 | C48: Depósito Recisão sem justa causa | E48: 0.027 | F48: 0.0203
B49: C5 | C49: Indenização Adicional | E49: 0.0041 | F49: 0.0031
B50: C | C50: Total | E50: =SUBTOTAL(9,E45:E49) -> 0.1033 | F50: =SUBTOTAL(9,F45:F49) -> 0.078
B52: GRUPO D
B53: D1 | C53: Reincidência de Grupo A sobre Grupo B | E53: =ROUND(E42*E29,4) -> 0.0862 | F53: =ROUND(F42*F29,4) -> 0.0327
B54: D2 | C54: Reincidência de Grupo A sobre Aviso Prévio Trabalhado e Reincidência do FGTS sobre Aviso Prévio Indenizado | E54: =E29*E46+E27*E45 -> 0.0040518 | F54: =F29*F46+F27*F45 -> 0.0030722
B55: D | C55: Total | E55: =SUBTOTAL(9,E53:E54) -> 0.0902518 | F55: =ROUND(SUBTOTAL(9,F53:F54),4) -> 0.0358
B56: TOTAL (A+B+C+D) | E56: =SUM(E29,E42,E50,E55) -> 0.8555518 | F56: =SUM(F29,F42,F50,F55) -> 0.4757
B58: FONTE:
B59: 1. | C59: SINAPI - Encargos Sociais a partir de agosto de 2023.
B61: NOTAS:
B62: 1. | C62: Deverão ser obedecidas as legislações trabalhistas e tributária vigentes, inclusive acordos de classes, sob pena de desclassificação da Proposta de Preços;
B63: 2. | C63: É de responsabilidade da proponente a adequação de todas as fórmulas utilizadas na planilha orçamentária.
B66: ________________________________________________________________________________
B71: ='DADOS GERAIS'!C24 -> Thaís Ferreira Pellaquim
B72: ='DADOS GERAIS'!C25 -> Engenheira Civil - CREA MG 247749/D

Sheet JUSTIFICATIVAS CPUS
B2: JUSTIFICATIVAS DE COMPOSIÇÕES DE PREÇO UNITÁRIO
B8: ='DADOS GERAIS'!B8 -> Secretaria de Atenção Especializada à Saúde | H8: BDI Geral: | I8: Encargo Social Mensalista: | J8: ='DADOS GERAIS'!$B$22 -> Data:
B9: ='DADOS GERAIS'!B9 -> Policlínica - Área Construída: 3.213,00 m² | H9: ='DADOS GERAIS'!C19 -> 0.24875249 | I9: ='ENCARGOS SOCIAIS'!F56 -> 0.4757 | J9: ='DADOS GERAIS'!$C$22 -> 09/05/2024
B11: ='DADOS GERAIS'!B11 -> Bancos: | H11: BDI Equipamentos: | I11: Encargo Social Horista: | J11: ='DADOS GERAIS'!$B$23 -> Revisão:
B12: ='DADOS GERAIS'!B12 -> SINAPI (11/2023) - CPOS/CDHU (11/2023) - SBC (11/2023) - ORSE (11/2023) - SEINFRA (028) - IOPES (11/2023) - CAERN (11/2023) - EMOP (11/2023) | H12: ='DADOS GERAIS'!C20 -> 0.16857591 | I12: ='ENCARGOS SOCIAIS'!E56 -> 0.8555518 | J12: ='DADOS GERAIS'!$C$23 -> 03
B15: ITEM | C15: COMPOSIÇÃO | D15: COMPOSIÇÃO DE REFERÊNCIA | E15: JUSTIFICATIVA
B16: 1 | C16: 02.02.150 | D16: CPOS/CDHU 02.02.150 | E16: Utilizada composição do CPOS para São Paulo visto que o SINAPI não possui composição adequada para contemplar tal serviço.
B17: 2 | C17: 02.02.130 | D17: CPOS/CDHU 02.02.130 | E17: Utilizada composição do CPOS para São Paulo visto que o SINAPI não possui composição adequada para contemplar tal serviço.
B18: 3 | C18: 02.02.160 | D18: CPOS/CDHU 02.02.160 | E18: Utilizada composição do CPOS para São Paulo visto que o SINAPI não possui composição adequada para contemplar tal serviço.
B19: 4 | C19: 02.02.140 | D19: CPOS/CDHU 02.02.140 | E19: Utilizada composição do CPOS para São Paulo visto que o SINAPI não possui composição adequada para contemplar tal serviço.
B20: 5 | C20: 05.07.040 | D20: CPOS/CDHU 05.07.040 | E20: Utilizada composição do CPOS para São Paulo visto que o SINAPI não possui composição adequada para contemplar tal serviço.
B21: 6 | C21: 012689 | D21: SBC 012689 | E21: Utilizada composição do SBC para São Paulo visto que o SINAPI não possui composição adequada para contemplar tal serviço.
B22: 7 | C22: 021101 | D22: SBC 021101 | E22: Utilizada composição do SBC para São Paulo visto que o SINAPI não possui composição adequada para contemplar tal serviço.
B23: 8 | C23: CPU1926 | D23: SINAPI 97063 + INSUMO SINAPI 20193 | E23: Junção do insumo de locação de andaime m2xmês com a montagem e desmontagem do andaime em m2, sendo coeficiente de 0,416 que corresponde à 1m2 em proporção à área do andaime informado no insumo.
B24: 9 | C24: CPU2096 | D24: Próprio CPU2096 | E24: Substituição do insumo SINAPI 00001525 pelo insumo SINAPI 00011145 para adequação da composição, conforme especificação de projeto.
B25: 10 | C25: 000128 | D25: SBC 000128 | E25: Utilizada composição do SBC para São Paulo visto que o SINAPI não possui composição adequada para contemplar tal serviço.
B26: 11 | C26: CPU2097 | D26: Próprio CPU2097 | E26: Substituição do insumo SINAPI 00001527 pelo insumo SINAPI 00011145 para adequação da composição, conforme especificação de projeto.
B27: 12 | C27: CPU2098 | D27: Próprio CPU2098 | E27: Substituição do insumo SINAPI 00038408 pelo insumo SINAPI 00011145 para adequação da composição, conforme especificação de projeto.
... B270: 255 | C270: 2451 | D270: ORSE 2451 | E270: Utilizada composição do ORSE visto que o SINAPI não possui composição adequada referente a esse serviço. Os preços praticados para esse serviço no estado de Sergipe são referenciais e exequíveis para o orçamento em São Paulo. Os insumos da composição ORSE que são SINAPI estão atualizados para o estado de São Paulo, portanto, somente insumos do ORSE que mantem preço na região de Sergipe.
